termplot/__init__.py
termplot/_version.py
termplot/etc.py
termplot/main.py
termplot/backend/__init__.py
termplot/backend/base_plotter.py
termplot/backend/matplotlib_plot.py
termplot/backend/terminal_plot.py
termplot/data_source/__init__.py
termplot/data_source/csv_source.py
termplot/data_source/jsonl.py
termplot/data_source/stdin_csv_source.py
termplot/data_source/tensorboard_source.py
termplot/monitor/__init__.py
termplot/monitor/fs_monitor.py
termplot/monitor/stdin_monitor.py
terminal_plot-2.2.2.dist-info/LICENSE
terminal_plot-2.2.2.dist-info/METADATA
terminal_plot-2.2.2.dist-info/WHEEL
terminal_plot-2.2.2.dist-info/entry_points.txt
terminal_plot-2.2.2.dist-info/top_level.txt
terminal_plot-2.2.2.dist-info/RECORD
