Metadata-Version: 2.1
Name: terminal-plot
Version: 2.2.2
Summary: View plotted stats directly inside terminal.
Home-page: https://github.com/soraxas/termplot
Author: Tin Lai (@soraxas)
Author-email: oscar@tinyiu.com
License: MIT
Keywords: tui termplot stats tensorboard csv
Classifier: Environment :: Console
Classifier: Framework :: Matplotlib
Classifier: Intended Audience :: Developers
Classifier: Intended Audience :: End Users/Desktop
Classifier: Intended Audience :: System Administrators
Classifier: License :: OSI Approved :: MIT License
Classifier: Operating System :: MacOS
Classifier: Operating System :: POSIX
Classifier: Operating System :: Unix
Classifier: Programming Language :: Python :: 3.6
Classifier: Programming Language :: Python :: 3.7
Classifier: Programming Language :: Python :: 3.8
Classifier: Programming Language :: Python :: 3.9
Classifier: Topic :: Desktop Environment
Classifier: Topic :: Terminals
Classifier: Topic :: Utilities
Requires-Python: >=3.6
License-File: LICENSE
Requires-Dist: tensorboard >=2.5
Requires-Dist: plotext ==5.2.8
Requires-Dist: loguru
Requires-Dist: mock
Requires-Dist: pandas
Requires-Dist: numpy
Requires-Dist: scipy
Requires-Dist: argcomplete
Requires-Dist: watchdog
Provides-Extra: matplotlib-backend
Requires-Dist: matplotlib ; extra == 'matplotlib-backend'
Requires-Dist: pillow ; extra == 'matplotlib-backend'
